py_nlp_utils/__init__.py
py_nlp_utils/deepseek_calc_tokens.py
py_nlp_utils/openai_calc_tokens.py
py_nlp_utils/transformers_calc_tokens.py
py_nlp_utils/who_is_unk.py
py_nlp_utils/deepseek_tokenizer/v2/tokenizer.json
py_nlp_utils/deepseek_tokenizer/v2/tokenizer_config.json
py_nlp_utils/deepseek_tokenizer/v3/tokenizer.json
py_nlp_utils/deepseek_tokenizer/v3/tokenizer_config.json
py_nlp_utils-0.0.1.dev5.dist-info/licenses/LICENSE
py_nlp_utils-0.0.1.dev5.dist-info/WHEEL
py_nlp_utils-0.0.1.dev5.dist-info/METADATA
py_nlp_utils-0.0.1.dev5.dist-info/RECORD
