Metadata-Version: 2.4
Name: py-nlp-utils
Version: 0.0.1.dev5
Summary: To avoid reimplemening simple NLP wheels
Keywords: nlp,utils,transformers,openai,deepseek
Author-email: Shen Fuchen <sfc@tju.edu.cn>
Requires-Python: >=3.7
License-Expression: MIT
Classifier: Development Status :: 4 - Beta
Classifier: Programming Language :: Python :: 3
Classifier: Operating System :: OS Independent
Classifier: Intended Audience :: Developers
Classifier: Intended Audience :: Science/Research
Classifier: Topic :: Utilities
License-File: LICENSE
Requires-Dist: transformers ; extra == "deepseek"
Requires-Dist: tiktoken ; extra == "openai"
Requires-Dist: transformers ; extra == "transformers"
Project-URL: Homepage, https://github.com/phuturesh/nlp_utils
Provides-Extra: deepseek
Provides-Extra: openai
Provides-Extra: transformers
